{"balance_sheet": {"years": [2019, 2018, 2017, 2016, 2015], "assets": {"Kassenbestand und Guthaben bei Kreditinstituten": [{"year": 2019, "value": 8.46}, {"year": 2018, "value": 7.66}, {"year": 2017, "value": 6.36}, {"year": 2016, "value": 5.69}, {"year": 2015, "value": 4.26}], "Forderungen aus Lieferungen und Leistungen": [{"year": 2019, "value": 7.99}, {"year": 2018, "value": 10.64}, {"year": 2017, "value": 11.28}, {"year": 2016, "value": 13.46}, {"year": 2015, "value": 18.35}], "Vorr\u00e4te": [{"year": 2019, "value": 15.47}, {"year": 2018, "value": 18.99}, {"year": 2017, "value": 18.68}, {"year": 2016, "value": 20.48}, {"year": 2015, "value": 21.63}], "Forderungen aus laufender Steuer": [{"year": 2019, "value": 0.83}, {"year": 2018, "value": 0.0}, {"year": 2017, "value": 0.34}, {"year": 2016, "value": 0.27}, {"year": 2015, "value": 0.85}], "Sonstiges Umlaufverm\u00f6gen": [{"year": 2019, "value": 0.23}, {"year": 2018, "value": 0.33}, {"year": 2017, "value": 0.37}, {"year": 2016, "value": 0.5}, {"year": 2015, "value": 0.0}], "Summe Umlaufverm\u00f6gen": [{"year": 2019, "value": 32.98}, {"year": 2018, "value": 37.63}, {"year": 2017, "value": 37.02}, {"year": 2016, "value": 40.4}, {"year": 2015, "value": 44.77}], "Sachanlagen": [{"year": 2019, "value": 2.0}, {"year": 2018, "value": 1.71}, {"year": 2017, "value": 1.75}, {"year": 2016, "value": 1.86}, {"year": 2015, "value": 2.77}], "Immaterielle Verm\u00f6gensgegenst\u00e4nde": [{"year": 2019, "value": 3.06}, {"year": 2018, "value": 3.03}, {"year": 2017, "value": 0.21}, {"year": 2016, "value": 0.15}, {"year": 2015, "value": 0.19}], "Finanzanlagen": [{"year": 2019, "value": 78.28}, {"year": 2018, "value": 76.76}, {"year": 2017, "value": 78.98}, {"year": 2016, "value": 80.04}, {"year": 2015, "value": 74.7}], "Sonstige Verm\u00f6gensgegenst\u00e4nde": [{"year": 2019, "value": 2.95}, {"year": 2018, "value": 0.61}, {"year": 2017, "value": 0.29}, {"year": 2016, "value": 0.27}, {"year": 2015, "value": 0.3}], "Summe Anlageverm\u00f6gen": [{"year": 2019, "value": 86.28}, {"year": 2018, "value": 82.11}, {"year": 2017, "value": 81.23}, {"year": 2016, "value": 82.33}, {"year": 2015, "value": 77.96}], "Latente Steuern": [{"year": 2019, "value": 2.37}, {"year": 2018, "value": 0.0}, {"year": 2017, "value": 0.0}, {"year": 2016, "value": 0.0}, {"year": 2015, "value": 0.0}], "Summe Aktiva": [{"year": 2019, "value": 119.26}, {"year": 2018, "value": 119.74}, {"year": 2017, "value": 118.25}, {"year": 2016, "value": 122.72}, {"year": 2015, "value": 122.73}]}, "liabilities_and_equity": {"Kurzfristige Finanzverbindlichkeiten": [{"year": 2019, "value": 6.42}, {"year": 2018, "value": 4.23}, {"year": 2017, "value": 5.58}, {"year": 2016, "value": 6.15}, {"year": 2015, "value": 11.61}], "Verbindlichkeiten aus Lieferung und Leistung": [{"year": 2019, "value": 2.64}, {"year": 2018, "value": 2.04}, {"year": 2017, "value": 2.6}, {"year": 2016, "value": 3.63}, {"year": 2015, "value": 3.44}], "Sonstiges kurzfristiges Fremdkapital": [{"year": 2019, "value": 19.21}, {"year": 2018, "value": 18.61}, {"year": 2017, "value": 15.44}, {"year": 2016, "value": 15.72}, {"year": 2015, "value": 21.94}], "Summe kurzfristiges Fremdkapital": [{"year": 2019, "value": 28.27}, {"year": 2018, "value": 24.88}, {"year": 2017, "value": 23.62}, {"year": 2016, "value": 25.5}, {"year": 2015, "value": 37.0}], "Langfristige Finanzverbindlichkeiten": [{"year": 2019, "value": 25.15}, {"year": 2018, "value": 30.94}, {"year": 2017, "value": 35.13}, {"year": 2016, "value": 39.22}, {"year": 2015, "value": 30.58}], "Pensionsr\u00fcckstellungen und \u00e4hnliche Verpflichtungen": [{"year": 2019, "value": 18.32}, {"year": 2018, "value": 16.62}, {"year": 2017, "value": 16.42}, {"year": 2016, "value": 17.19}, {"year": 2015, "value": 16.56}], "Summe langfristiges Fremdkapital": [{"year": 2019, "value": 54.29}, {"year": 2018, "value": 56.37}, {"year": 2017, "value": 59.54}, {"year": 2016, "value": 64.04}, {"year": 2015, "value": 54.56}], "Minderheitenanteil": [{"year": 2019, "value": 0.21}, {"year": 2018, "value": 0.21}, {"year": 2017, "value": 0.21}, {"year": 2016, "value": 0.21}, {"year": 2015, "value": 0.21}], "Latente Steuern": [{"year": 2019, "value": 7.85}, {"year": 2018, "value": 6.41}, {"year": 2017, "value": 7.63}, {"year": 2016, "value": 7.31}, {"year": 2015, "value": 7.19}], "Summe Fremdkapital": [{"year": 2019, "value": 82.57}, {"year": 2018, "value": 81.26}, {"year": 2017, "value": 83.15}, {"year": 2016, "value": 89.54}, {"year": 2015, "value": 91.56}], "Eigene Aktien": [{"year": 2019, "value": -0.25}, {"year": 2018, "value": -0.25}, {"year": 2017, "value": -0.26}, {"year": 2016, "value": -0.25}, {"year": 2015, "value": -0.25}], "Sonstiges Kapital": [{"year": 2019, "value": 0.56}, {"year": 2018, "value": 1.73}, {"year": 2017, "value": 3.78}, {"year": 2016, "value": 3.74}, {"year": 2015, "value": 4.12}], "Gezeichnetes Kapital (Grundkapital)": [{"year": 2019, "value": 11.0}, {"year": 2018, "value": 11.0}, {"year": 2017, "value": 11.0}, {"year": 2016, "value": 11.0}, {"year": 2015, "value": 11.0}], "Gewinnr\u00fccklagen": [{"year": 2019, "value": 25.18}, {"year": 2018, "value": 25.79}, {"year": 2017, "value": 20.36}, {"year": 2016, "value": 18.48}, {"year": 2015, "value": 16.09}], "wirtschaftliches Eigenkapital": [{"year": 2019, "value": 36.48}, {"year": 2018, "value": 37.44}, {"year": 2017, "value": 34.06}, {"year": 2016, "value": 32.15}, {"year": 2015, "value": 30.96}], "Summe Eigenkapital": [{"year": 2019, "value": 36.48}, {"year": 2018, "value": 38.26}, {"year": 2017, "value": 34.88}, {"year": 2016, "value": 32.97}, {"year": 2015, "value": 30.96}], "Summe Passiva": [{"year": 2019, "value": 119.26}, {"year": 2018, "value": 119.74}, {"year": 2017, "value": 118.25}, {"year": 2016, "value": 122.72}, {"year": 2015, "value": 122.73}]}}, "head": {"title": "DIERIG HOLDING AG INHABER-AKTIEN O.N.", "current_price": {"value": 12.9, "currency": "EUR"}, "isin": "DE0005580005", "wkn": "558000", "timestamp": "2020-09-08 00:55:22", "url": "https://kurse.boerse.ard.de/ard/kurse_einzelkurs_profil.htn?i=100063", "sector": "Handel"}, "owner_structure": [{"owner": "Textil-Treuhand GmbH", "percent": 0.701}, {"owner": "Streubesitz", "percent": 0.197}, {"owner": "SPR Treuhand- und...", "percent": 0.049}, {"owner": "Eva und Johannes W...", "percent": 0.03}, {"owner": "eigene Anteile", "percent": 0.023}], "kpi": {"years": [2019, 2018, 2017, 2016, 2015], "revenue": [{"year": 2019, "value": 58.71}, {"year": 2018, "value": 59.85}, {"year": 2017, "value": 66.54}, {"year": 2016, "value": 68.36}, {"year": 2015, "value": 75.92}], "operatingProfit": [{"year": 2019, "value": 1.33}, {"year": 2018, "value": 5.52}, {"year": 2017, "value": 5.0}, {"year": 2016, "value": 6.05}, {"year": 2015, "value": 7.35}], "earnings": [{"year": 2019, "value": 0.28}, {"year": 2018, "value": 3.06}, {"year": 2017, "value": 2.53}, {"year": 2016, "value": 2.69}, {"year": 2015, "value": 3.83}], "bookValuePerShare": [{"year": 2019, "value": 8.89}, {"year": 2018, "value": 9.33}, {"year": 2017, "value": 8.5}, {"year": 2016, "value": 8.04}, {"year": 2015, "value": 7.54}], "cashFlow": [{"year": 2019, "value": 8.79}, {"year": 2018, "value": 6.41}, {"year": 2017, "value": 7.27}, {"year": 2016, "value": 1.22}, {"year": 2015, "value": 5.24}], "cashFlowFromInvestments": [{"year": 2019, "value": -3.85}, {"year": 2018, "value": -2.58}, {"year": 2017, "value": -1.18}, {"year": 2016, "value": -2.64}, {"year": 2015, "value": -11.14}], "cashFlowFromFinance": [{"year": 2019, "value": -4.26}, {"year": 2018, "value": -3.52}, {"year": 2017, "value": -5.38}, {"year": 2016, "value": 2.9}, {"year": 2015, "value": 6.56}], "cashReserveDelta": [{"year": 2019, "value": 0.8}, {"year": 2018, "value": 1.3}, {"year": 2017, "value": 0.67}, {"year": 2016, "value": 1.43}, {"year": 2015, "value": 0.85}], "cashReserveEndOfPeriod": [{"year": 2019, "value": 8.46}, {"year": 2018, "value": 7.66}, {"year": 2017, "value": 6.36}, {"year": 2016, "value": 5.69}, {"year": 2015, "value": 4.26}], "amountOfSharesOutstanding": [{"year": 2019, "value": 4.2}, {"year": 2018, "value": 4.2}, {"year": 2017, "value": 4.2}, {"year": 2016, "value": 4.2}, {"year": 2015, "value": 4.2}], "earningsPerShare": [{"year": 2019, "value": 0.07}, {"year": 2018, "value": 0.75}, {"year": 2017, "value": 0.62}, {"year": 2016, "value": 0.66}, {"year": 2015, "value": 0.93}], "dividendPerShare": [{"year": 2019, "value": 0.0}, {"year": 2018, "value": 0.2}, {"year": 2017, "value": 0.2}, {"year": 2016, "value": 0.2}, {"year": 2015, "value": 0.0}], "dividend": [{"year": 2019, "value": 0.0}, {"year": 2018, "value": 0.82}, {"year": 2017, "value": 0.82}, {"year": 2016, "value": 0.82}, {"year": 2015, "value": 0.0}], "revenuePerStock": [{"year": 2019, "value": 13.98}, {"year": 2018, "value": 14.25}, {"year": 2017, "value": 15.84}, {"year": 2016, "value": 16.28}, {"year": 2015, "value": 18.08}], "cashFlowPerStock": [{"year": 2019, "value": 2.09}, {"year": 2018, "value": 1.53}, {"year": 2017, "value": 1.73}, {"year": 2016, "value": 0.29}, {"year": 2015, "value": 1.25}], "returnOnEquity": [{"year": 2019, "value": 0.76}, {"year": 2018, "value": 8.01}, {"year": 2017, "value": 7.25}, {"year": 2016, "value": 8.16}, {"year": 2015, "value": 12.38}], "returnOnRevenue": [{"year": 2019, "value": 0.47}, {"year": 2018, "value": 5.12}, {"year": 2017, "value": 3.8}, {"year": 2016, "value": 3.94}, {"year": 2015, "value": 5.05}], "totalReturn": [{"year": 2019, "value": 1.29}, {"year": 2018, "value": 3.72}, {"year": 2017, "value": 3.36}, {"year": 2016, "value": 3.96}, {"year": 2015, "value": 4.72}], "returnOnInvest": [{"year": 2019, "value": 0.23}, {"year": 2018, "value": 2.56}, {"year": 2017, "value": 2.14}, {"year": 2016, "value": 2.19}, {"year": 2015, "value": 3.12}], "shareOfLongTermAssets": [{"year": 2019, "value": 72.34}, {"year": 2018, "value": 68.57}, {"year": 2017, "value": 68.69}, {"year": 2016, "value": 67.08}, {"year": 2015, "value": 63.52}], "shareOfCurrentAssets": [{"year": 2019, "value": 27.66}, {"year": 2018, "value": 31.43}, {"year": 2017, "value": 31.31}, {"year": 2016, "value": 32.92}, {"year": 2015, "value": 36.48}], "shareOfEquity": [{"year": 2019, "value": 30.59}, {"year": 2018, "value": 31.96}, {"year": 2017, "value": 29.5}, {"year": 2016, "value": 26.87}, {"year": 2015, "value": 25.22}], "debtToEquityRatio": [{"year": 2019, "value": 226.92}, {"year": 2018, "value": 212.91}, {"year": 2017, "value": 239.01}, {"year": 2016, "value": 272.2}, {"year": 2015, "value": 296.45}], "firstGradeLiquidity": [{"year": 2019, "value": 29.91}, {"year": 2018, "value": 30.78}, {"year": 2017, "value": 26.92}, {"year": 2016, "value": 22.32}, {"year": 2015, "value": 11.52}], "secondGradeLiquidity": [{"year": 2019, "value": 58.19}, {"year": 2018, "value": 73.53}, {"year": 2017, "value": 74.67}, {"year": 2016, "value": 75.1}, {"year": 2015, "value": 61.1}], "thirdGradeLiquidity": [{"year": 2019, "value": 112.89}, {"year": 2018, "value": 149.86}, {"year": 2017, "value": 153.75}, {"year": 2016, "value": 155.43}, {"year": 2015, "value": 119.56}], "firstCoverageRatio": [{"year": 2019, "value": 42.28}, {"year": 2018, "value": 46.6}, {"year": 2017, "value": 42.94}, {"year": 2016, "value": 40.05}, {"year": 2015, "value": 39.71}], "secondCoverageRatio": [{"year": 2019, "value": 105.21}, {"year": 2018, "value": 115.26}, {"year": 2017, "value": 116.23}, {"year": 2016, "value": 117.84}, {"year": 2015, "value": 109.7}], "thirdCoverageRatio": [{"year": 2019, "value": 89.22}, {"year": 2018, "value": 93.61}, {"year": 2017, "value": 94.5}, {"year": 2016, "value": 94.36}, {"year": 2015, "value": 85.87}], "gearingRatio": [{"year": 2019, "value": 69.41}, {"year": 2018, "value": 68.04}, {"year": 2017, "value": 70.5}, {"year": 2016, "value": 73.13}, {"year": 2015, "value": 74.78}], "amountOfEmployees": [{"year": 2019, "value": 187.0}, {"year": 2018, "value": 200.0}, {"year": 2017, "value": 189.0}, {"year": 2016, "value": 195.0}, {"year": 2015, "value": 198.0}], "laborCost": [{"year": 2019, "value": 11.2}, {"year": 2018, "value": 10.69}, {"year": 2017, "value": 10.39}, {"year": 2016, "value": 10.42}, {"year": 2015, "value": 10.36}], "revenuePerEmployee": [{"year": 2019, "value": 313950.42}, {"year": 2018, "value": 299243.26}, {"year": 2017, "value": 352080.74}, {"year": 2016, "value": 350586.9}, {"year": 2015, "value": 383425.42}]}}