{"balance_sheet": {"years": [2019, 2018, 2017, 2016, 2015], "assets": {"Kassenbestand und Guthaben bei Kreditinstituten": [{"year": 2019, "value": 55021.0}, {"year": 2018, "value": 41250.0}, {"year": 2017, "value": 30986.0}, {"year": 2016, "value": 25981.0}, {"year": 2015, "value": 19808.0}], "Forderungen aus Lieferungen und Leistungen": [{"year": 2019, "value": 20816.0}, {"year": 2018, "value": 16677.0}, {"year": 2017, "value": 13164.0}, {"year": 2016, "value": 8339.0}, {"year": 2015, "value": 6423.0}], "Vorr\u00e4te": [{"year": 2019, "value": 20497.0}, {"year": 2018, "value": 17174.0}, {"year": 2017, "value": 16047.0}, {"year": 2016, "value": 11461.0}, {"year": 2015, "value": 10243.0}], "Forderungen aus laufender Steuer": [{"year": 2019, "value": 0.0}, {"year": 2018, "value": 0.0}, {"year": 2017, "value": 0.0}, {"year": 2016, "value": 0.0}, {"year": 2015, "value": 0.0}], "Sonstiges Umlaufverm\u00f6gen": [{"year": 2019, "value": 0.0}, {"year": 2018, "value": 0.0}, {"year": 2017, "value": 0.0}, {"year": 2016, "value": 0.0}, {"year": 2015, "value": 0.0}], "Summe Umlaufverm\u00f6gen": [{"year": 2019, "value": 96334.0}, {"year": 2018, "value": 75101.0}, {"year": 2017, "value": 60197.0}, {"year": 2016, "value": 45781.0}, {"year": 2015, "value": 36474.0}], "Sachanlagen": [{"year": 2019, "value": 72705.0}, {"year": 2018, "value": 61797.0}, {"year": 2017, "value": 48866.0}, {"year": 2016, "value": 29114.0}, {"year": 2015, "value": 21838.0}], "Immaterielle Verm\u00f6gensgegenst\u00e4nde": [{"year": 2019, "value": 14754.0}, {"year": 2018, "value": 14548.0}, {"year": 2017, "value": 13350.0}, {"year": 2016, "value": 3784.0}, {"year": 2015, "value": 3759.0}], "Goodwill": [{"year": 2019, "value": 14754.0}, {"year": 2018, "value": 14548.0}, {"year": 2017, "value": 13350.0}, {"year": 2016, "value": 3784.0}, {"year": 2015, "value": 3759.0}], "Summe Anlageverm\u00f6gen": [{"year": 2019, "value": 128914.0}, {"year": 2018, "value": 87547.0}, {"year": 2017, "value": 71113.0}, {"year": 2016, "value": 37621.0}, {"year": 2015, "value": 28970.0}], "Summe Aktiva": [{"year": 2019, "value": 225248.0}, {"year": 2018, "value": 162648.0}, {"year": 2017, "value": 131310.0}, {"year": 2016, "value": 83402.0}, {"year": 2015, "value": 65444.0}]}, "liabilities_and_equity": {"Kurzfristige Finanzverbindlichkeiten": [{"year": 2019, "value": 0.0}, {"year": 2018, "value": 0.0}, {"year": 2017, "value": 0.0}, {"year": 2016, "value": 0.0}, {"year": 2015, "value": 0.0}], "Verbindlichkeiten aus Lieferung und Leistung": [{"year": 2019, "value": 47183.0}, {"year": 2018, "value": 38192.0}, {"year": 2017, "value": 34616.0}, {"year": 2016, "value": 25309.0}, {"year": 2015, "value": 20397.0}], "Sonstiges kurzfristiges Fremdkapital": [{"year": 2019, "value": 40629.0}, {"year": 2018, "value": 30199.0}, {"year": 2017, "value": 23267.0}, {"year": 2016, "value": 18507.0}, {"year": 2015, "value": 13502.0}], "Verbindlichkeiten aus laufender Steuer": [{"year": 2019, "value": 0.0}, {"year": 2018, "value": 0.0}, {"year": 2017, "value": 0.0}, {"year": 2016, "value": 0.0}, {"year": 2015, "value": 0.0}], "Summe kurzfristiges Fremdkapital": [{"year": 2019, "value": 87812.0}, {"year": 2018, "value": 68391.0}, {"year": 2017, "value": 57883.0}, {"year": 2016, "value": 43816.0}, {"year": 2015, "value": 33899.0}], "Langfristige Finanzverbindlichkeiten": [{"year": 2019, "value": 63205.0}, {"year": 2018, "value": 39787.0}, {"year": 2017, "value": 37926.0}, {"year": 2016, "value": 15213.0}, {"year": 2015, "value": 14183.0}], "Summe langfristiges Fremdkapital": [{"year": 2019, "value": 75376.0}, {"year": 2018, "value": 50708.0}, {"year": 2017, "value": 45718.0}, {"year": 2016, "value": 20301.0}, {"year": 2015, "value": 18161.0}], "Minderheitenanteil": [{"year": 2019, "value": 0.0}, {"year": 2018, "value": 0.0}, {"year": 2017, "value": 0.0}, {"year": 2016, "value": 0.0}, {"year": 2015, "value": 0.0}], "Rechnungsabgrenzungsposten": [{"year": 2019, "value": 8190.0}, {"year": 2018, "value": 6536.0}, {"year": 2017, "value": 5097.0}, {"year": 2016, "value": 4768.0}, {"year": 2015, "value": 3118.0}], "Summe Fremdkapital": [{"year": 2019, "value": 163188.0}, {"year": 2018, "value": 119099.0}, {"year": 2017, "value": 103601.0}, {"year": 2016, "value": 64117.0}, {"year": 2015, "value": 52060.0}], "Eigene Aktien": [{"year": 2019, "value": -1837.0}, {"year": 2018, "value": -1837.0}, {"year": 2017, "value": -1837.0}, {"year": 2016, "value": -1837.0}, {"year": 2015, "value": -1837.0}], "Sonstiges Kapital": [{"year": 2019, "value": -986.14}, {"year": 2018, "value": -1035.14}, {"year": 2017, "value": -484.07}, {"year": 2016, "value": -985.0}, {"year": 2015, "value": -722.94}], "Gezeichnetes Kapital (Grundkapital)": [{"year": 2019, "value": 5.14}, {"year": 2018, "value": 5.14}, {"year": 2017, "value": 5.07}, {"year": 2016, "value": 5.0}, {"year": 2015, "value": 4.94}], "Kapitalr\u00fccklagen": [{"year": 2019, "value": 33658.0}, {"year": 2018, "value": 26791.0}, {"year": 2017, "value": 21389.0}, {"year": 2016, "value": 17186.0}, {"year": 2015, "value": 13394.0}], "Gewinnr\u00fccklagen": [{"year": 2019, "value": 31220.0}, {"year": 2018, "value": 19625.0}, {"year": 2017, "value": 8636.0}, {"year": 2016, "value": 4916.0}, {"year": 2015, "value": 2545.0}], "wirtschaftliches Eigenkapital": [{"year": 2019, "value": 62060.0}, {"year": 2018, "value": 43549.0}, {"year": 2017, "value": 27709.0}, {"year": 2016, "value": 19285.0}, {"year": 2015, "value": 13384.0}], "Summe Eigenkapital": [{"year": 2019, "value": 62060.0}, {"year": 2018, "value": 43549.0}, {"year": 2017, "value": 27709.0}, {"year": 2016, "value": 19285.0}, {"year": 2015, "value": 13384.0}], "Summe Passiva": [{"year": 2019, "value": 225248.0}, {"year": 2018, "value": 162648.0}, {"year": 2017, "value": 131310.0}, {"year": 2016, "value": 83402.0}, {"year": 2015, "value": 65444.0}]}}, "head": {"title": "AMAZON.COM INC. REGISTERED SHARES DL -,01", "current_price": {"value": 2770.0, "currency": "EUR"}, "isin": "US0231351067", "wkn": "906866", "timestamp": "2020-09-08 00:52:47", "url": "https://kurse.boerse.ard.de/ard/kurse_einzelkurs_profil.htn?i=129667", "sector": "Handel"}, "owner_structure": [{"owner": "Streubesitz", "percent": 0.681}, {"owner": "Jeffrey P. Bezos", "percent": 0.16}, {"owner": "The Vanguard Group, Inc.", "percent": 0.062}, {"owner": "BlackRock, Inc.", "percent": 0.052}, {"owner": "eigene Anteile", "percent": 0.045}], "kpi": {"years": [2019, 2018, 2017, 2016, 2015], "revenue": [{"year": 2019, "value": 280522.0}, {"year": 2018, "value": 232887.0}, {"year": 2017, "value": 177866.0}, {"year": 2016, "value": 135987.0}, {"year": 2015, "value": 107006.0}], "operatingProfit": [{"year": 2019, "value": 14730.0}, {"year": 2018, "value": 12247.0}, {"year": 2017, "value": 4448.0}, {"year": 2016, "value": 4180.0}, {"year": 2015, "value": 1977.0}], "earnings": [{"year": 2019, "value": 11588.0}, {"year": 2018, "value": 10073.0}, {"year": 2017, "value": 3033.0}, {"year": 2016, "value": 2371.0}, {"year": 2015, "value": 596.0}], "bookValuePerShare": [{"year": 2019, "value": 126.4}, {"year": 2018, "value": 88.69}, {"year": 2017, "value": 57.25}, {"year": 2016, "value": 40.43}, {"year": 2015, "value": 28.42}], "cashFlow": [{"year": 2019, "value": 38514.0}, {"year": 2018, "value": 30723.0}, {"year": 2017, "value": 18434.0}, {"year": 2016, "value": 16443.0}, {"year": 2015, "value": 11920.0}], "cashFlowFromInvestments": [{"year": 2019, "value": -24281.0}, {"year": 2018, "value": -12369.0}, {"year": 2017, "value": -27819.0}, {"year": 2016, "value": -9876.0}, {"year": 2015, "value": -6450.0}], "cashFlowFromFinance": [{"year": 2019, "value": -10066.0}, {"year": 2018, "value": -7686.0}, {"year": 2017, "value": 9860.0}, {"year": 2016, "value": -2911.0}, {"year": 2015, "value": -3763.0}], "cashReserveDelta": [{"year": 2019, "value": 13771.0}, {"year": 2018, "value": 10264.0}, {"year": 2017, "value": 5005.0}, {"year": 2016, "value": 6173.0}, {"year": 2015, "value": 2392.0}], "cashReserveEndOfPeriod": [{"year": 2019, "value": 55021.0}, {"year": 2018, "value": 41250.0}, {"year": 2017, "value": 30986.0}, {"year": 2016, "value": 25981.0}, {"year": 2015, "value": 19808.0}], "amountOfSharesOutstanding": [{"year": 2019, "value": 504.0}, {"year": 2018, "value": 500.0}, {"year": 2017, "value": 493.0}, {"year": 2016, "value": 484.0}, {"year": 2015, "value": 477.0}], "earningsPerShare": [{"year": 2019, "value": 23.01}, {"year": 2018, "value": 20.14}, {"year": 2017, "value": 6.15}, {"year": 2016, "value": 4.9}, {"year": 2015, "value": 1.25}], "dividendPerShare": [{"year": 2019, "value": 0.0}, {"year": 2018, "value": 0.0}, {"year": 2017, "value": 0.0}, {"year": 2016, "value": 0.0}, {"year": 2015, "value": 0.0}], "dividend": [{"year": 2019, "value": 0.0}, {"year": 2018, "value": 0.0}, {"year": 2017, "value": 0.0}, {"year": 2016, "value": 0.0}, {"year": 2015, "value": 0.0}], "revenuePerStock": [{"year": 2019, "value": 545.76}, {"year": 2018, "value": 453.09}, {"year": 2017, "value": 350.82}, {"year": 2016, "value": 271.97}, {"year": 2015, "value": 216.61}], "cashFlowPerStock": [{"year": 2019, "value": 74.93}, {"year": 2018, "value": 59.77}, {"year": 2017, "value": 36.36}, {"year": 2016, "value": 32.89}, {"year": 2015, "value": 24.13}], "returnOnEquity": [{"year": 2019, "value": 18.67}, {"year": 2018, "value": 23.13}, {"year": 2017, "value": 10.95}, {"year": 2016, "value": 12.29}, {"year": 2015, "value": 4.45}], "returnOnRevenue": [{"year": 2019, "value": 4.13}, {"year": 2018, "value": 4.33}, {"year": 2017, "value": 1.71}, {"year": 2016, "value": 1.74}, {"year": 2015, "value": 0.56}], "totalReturn": [{"year": 2019, "value": 5.85}, {"year": 2018, "value": 7.06}, {"year": 2017, "value": 2.96}, {"year": 2016, "value": 3.42}, {"year": 2015, "value": 1.61}], "returnOnInvest": [{"year": 2019, "value": 5.14}, {"year": 2018, "value": 6.19}, {"year": 2017, "value": 2.31}, {"year": 2016, "value": 2.84}, {"year": 2015, "value": 0.91}], "shareOfLongTermAssets": [{"year": 2019, "value": 57.23}, {"year": 2018, "value": 53.83}, {"year": 2017, "value": 54.16}, {"year": 2016, "value": 45.11}, {"year": 2015, "value": 44.27}], "shareOfCurrentAssets": [{"year": 2019, "value": 42.77}, {"year": 2018, "value": 46.17}, {"year": 2017, "value": 45.84}, {"year": 2016, "value": 54.89}, {"year": 2015, "value": 55.73}], "shareOfEquity": [{"year": 2019, "value": 27.55}, {"year": 2018, "value": 26.77}, {"year": 2017, "value": 21.1}, {"year": 2016, "value": 23.12}, {"year": 2015, "value": 20.45}], "debtToEquityRatio": [{"year": 2019, "value": 262.95}, {"year": 2018, "value": 273.48}, {"year": 2017, "value": 373.89}, {"year": 2016, "value": 332.47}, {"year": 2015, "value": 388.97}], "firstGradeLiquidity": [{"year": 2019, "value": 62.66}, {"year": 2018, "value": 60.31}, {"year": 2017, "value": 53.53}, {"year": 2016, "value": 59.3}, {"year": 2015, "value": 58.43}], "secondGradeLiquidity": [{"year": 2019, "value": 86.36}, {"year": 2018, "value": 84.7}, {"year": 2017, "value": 76.27}, {"year": 2016, "value": 78.33}, {"year": 2015, "value": 77.38}], "thirdGradeLiquidity": [{"year": 2019, "value": 109.7}, {"year": 2018, "value": 109.81}, {"year": 2017, "value": 104.0}, {"year": 2016, "value": 104.48}, {"year": 2015, "value": 107.6}], "firstCoverageRatio": [{"year": 2019, "value": 48.14}, {"year": 2018, "value": 49.74}, {"year": 2017, "value": 38.96}, {"year": 2016, "value": 51.26}, {"year": 2015, "value": 46.2}], "secondCoverageRatio": [{"year": 2019, "value": 106.61}, {"year": 2018, "value": 107.66}, {"year": 2017, "value": 103.25}, {"year": 2016, "value": 105.22}, {"year": 2015, "value": 108.89}], "thirdCoverageRatio": [{"year": 2019, "value": 91.99}, {"year": 2018, "value": 90.01}, {"year": 2017, "value": 84.24}, {"year": 2016, "value": 80.65}, {"year": 2015, "value": 80.45}], "gearingRatio": [{"year": 2019, "value": 72.45}, {"year": 2018, "value": 73.23}, {"year": 2017, "value": 78.9}, {"year": 2016, "value": 76.88}, {"year": 2015, "value": 79.55}], "amountOfEmployees": [{"year": 2019, "value": 798000.0}, {"year": 2018, "value": 647500.0}, {"year": 2017, "value": 566000.0}, {"year": 2016, "value": 341400.0}, {"year": 2015, "value": 230800.0}], "revenuePerEmployee": [{"year": 2019, "value": 351531.33}, {"year": 2018, "value": 359671.04}, {"year": 2017, "value": 314250.88}, {"year": 2016, "value": 398321.62}, {"year": 2015, "value": 463630.85}]}}