{"balance_sheet": {"years": [2018, 2017, 2016, 2015, 2014], "assets": {"Kassenbestand und Guthaben bei Kreditinstituten": [{"year": 2018, "value": 17388.0}, {"year": 2017, "value": 13582.0}, {"year": 2016, "value": 12078.0}, {"year": 2015, "value": 10510.0}, {"year": 2014, "value": 11895.0}], "Forderungen aus Lieferungen und Leistungen": [{"year": 2018, "value": 9520.0}, {"year": 2017, "value": 10182.0}, {"year": 2016, "value": 11186.0}, {"year": 2015, "value": 12022.0}, {"year": 2014, "value": 19709.0}], "Vorr\u00e4te": [{"year": 2018, "value": 4651.0}, {"year": 2017, "value": 4621.0}, {"year": 2016, "value": 4637.0}, {"year": 2015, "value": 3910.0}, {"year": 2014, "value": 7555.0}], "Sonstiges Umlaufverm\u00f6gen": [{"year": 2018, "value": 7891.0}, {"year": 2017, "value": 8048.0}, {"year": 2016, "value": 10084.0}, {"year": 2015, "value": 31056.0}, {"year": 2014, "value": 15704.0}], "Summe Umlaufverm\u00f6gen": [{"year": 2018, "value": 39450.0}, {"year": 2017, "value": 36433.0}, {"year": 2016, "value": 37985.0}, {"year": 2015, "value": 57498.0}, {"year": 2014, "value": 54863.0}], "Sachanlagen": [{"year": 2018, "value": 60302.0}, {"year": 2017, "value": 63158.0}, {"year": 2016, "value": 70793.0}, {"year": 2015, "value": 63795.0}, {"year": 2014, "value": 71962.0}], "Immaterielle Verm\u00f6gensgegenst\u00e4nde": [{"year": 2018, "value": 3170.0}, {"year": 2017, "value": 2925.0}, {"year": 2016, "value": 3269.0}, {"year": 2015, "value": 2433.0}, {"year": 2014, "value": 3645.0}], "Goodwill": [{"year": 2018, "value": 1284.0}, {"year": 2017, "value": 1204.0}, {"year": 2016, "value": 1320.0}, {"year": 2015, "value": 1314.0}, {"year": 2014, "value": 2197.0}], "Finanzanlagen": [{"year": 2018, "value": 9216.0}, {"year": 2017, "value": 5405.0}, {"year": 2016, "value": 6176.0}, {"year": 2015, "value": 4051.0}, {"year": 2014, "value": 6152.0}], "Summe Anlageverm\u00f6gen": [{"year": 2018, "value": 78923.0}, {"year": 2017, "value": 78172.0}, {"year": 2016, "value": 86560.0}, {"year": 2015, "value": 77294.0}, {"year": 2014, "value": 91344.0}], "Latente Steuern": [{"year": 2018, "value": 3931.0}, {"year": 2017, "value": 4078.0}, {"year": 2016, "value": 3790.0}, {"year": 2015, "value": 4349.0}, {"year": 2014, "value": 5231.0}], "Summe Aktiva": [{"year": 2018, "value": 118373.0}, {"year": 2017, "value": 114928.0}, {"year": 2016, "value": 124545.0}, {"year": 2015, "value": 134792.0}, {"year": 2014, "value": 146207.0}]}, "liabilities_and_equity": {"Kurzfristige Finanzverbindlichkeiten": [{"year": 2018, "value": 5783.0}, {"year": 2017, "value": 4528.0}, {"year": 2016, "value": 6675.0}, {"year": 2015, "value": 8383.0}, {"year": 2014, "value": 6575.0}], "Verbindlichkeiten aus Lieferung und Leistung": [{"year": 2018, "value": 11645.0}, {"year": 2017, "value": 10890.0}, {"year": 2016, "value": 11038.0}, {"year": 2015, "value": 9345.0}, {"year": 2014, "value": 15015.0}], "Sonstiges kurzfristiges Fremdkapital": [{"year": 2018, "value": 10747.0}, {"year": 2017, "value": 8520.0}, {"year": 2016, "value": 9457.0}, {"year": 2015, "value": 18270.0}, {"year": 2014, "value": 13471.0}], "Erhaltene Anzahlungen": [{"year": 2018, "value": 207.0}, {"year": 2017, "value": 797.0}, {"year": 2016, "value": 526.0}, {"year": 2015, "value": 637.0}, {"year": 2014, "value": 2278.0}], "Summe kurzfristiges Fremdkapital": [{"year": 2018, "value": 28382.0}, {"year": 2017, "value": 24735.0}, {"year": 2016, "value": 27696.0}, {"year": 2015, "value": 36635.0}, {"year": 2014, "value": 37339.0}], "Langfristige Finanzverbindlichkeiten": [{"year": 2018, "value": 20082.0}, {"year": 2017, "value": 20179.0}, {"year": 2016, "value": 20564.0}, {"year": 2015, "value": 19393.0}, {"year": 2014, "value": 19316.0}], "Pensionsr\u00fcckstellungen und \u00e4hnliche Verpflichtungen": [{"year": 2018, "value": 1117.0}, {"year": 2017, "value": 1022.0}, {"year": 2016, "value": 868.0}, {"year": 2015, "value": 1056.0}, {"year": 2014, "value": 1313.0}], "Summe langfristiges Fremdkapital": [{"year": 2018, "value": 38859.0}, {"year": 2017, "value": 42027.0}, {"year": 2016, "value": 43763.0}, {"year": 2015, "value": 44488.0}, {"year": 2014, "value": 46659.0}], "Minderheitenanteil": [{"year": 2018, "value": 57.0}, {"year": 2017, "value": 49.0}, {"year": 2016, "value": 49.0}, {"year": 2015, "value": 1916.0}, {"year": 2014, "value": 2455.0}], "Latente Steuern": [{"year": 2018, "value": 4272.0}, {"year": 2017, "value": 5900.0}, {"year": 2016, "value": 6667.0}, {"year": 2015, "value": 6921.0}, {"year": 2014, "value": 7847.0}], "Summe Fremdkapital": [{"year": 2018, "value": 67241.0}, {"year": 2017, "value": 66762.0}, {"year": 2016, "value": 71459.0}, {"year": 2015, "value": 81123.0}, {"year": 2014, "value": 83998.0}], "Eigene Aktien": [{"year": 2018, "value": -581.0}, {"year": 2017, "value": -581.0}, {"year": 2016, "value": -581.0}, {"year": 2015, "value": -581.0}, {"year": 2014, "value": -581.0}], "Sonstiges Kapital": [{"year": 2018, "value": 10889.64}, {"year": 2017, "value": 8639.64}, {"year": 2016, "value": 10686.64}, {"year": 2015, "value": -643.36}, {"year": 2014, "value": 10262.64}], "Gezeichnetes Kapital (Grundkapital)": [{"year": 2018, "value": 4005.36}, {"year": 2017, "value": 4005.36}, {"year": 2016, "value": 4005.36}, {"year": 2015, "value": 4005.36}, {"year": 2014, "value": 4005.36}], "Gewinnr\u00fccklagen": [{"year": 2018, "value": 36702.0}, {"year": 2017, "value": 35966.0}, {"year": 2016, "value": 40367.0}, {"year": 2015, "value": 48972.0}, {"year": 2014, "value": 46067.0}], "wirtschaftliches Eigenkapital": [{"year": 2018, "value": 48027.05}, {"year": 2017, "value": 46589.54}, {"year": 2016, "value": 51596.0}, {"year": 2015, "value": 48873.0}, {"year": 2014, "value": 55717.0}], "Summe Eigenkapital": [{"year": 2018, "value": 51016.0}, {"year": 2017, "value": 48030.0}, {"year": 2016, "value": 54478.0}, {"year": 2015, "value": 51753.0}, {"year": 2014, "value": 59754.0}], "Summe Passiva": [{"year": 2018, "value": 118373.0}, {"year": 2017, "value": 114928.0}, {"year": 2016, "value": 124545.0}, {"year": 2015, "value": 134792.0}, {"year": 2014, "value": 146207.0}]}}, "head": {"title": "ENI S.P.A. AZIONI NOM. O.N.", "current_price": {"value": 13.83, "currency": "EUR"}, "isin": "IT0003132476", "wkn": "897791", "timestamp": "2019-10-12 18:17:43", "url": "https://kurse.boerse.ard.de/ard/kurse_einzelkurs_profil.htn?i=127274"}, "owner_structure": [{"owner": "Streubesitz", "percent": 0.69}, {"owner": "Cassa Depositi e Prestiti...", "percent": 0.258}, {"owner": "Ministero dell 'Economia...", "percent": 0.043}, {"owner": "eigene Anteile", "percent": 0.009}], "kpi": {"years": [2018, 2017, 2016, 2015, 2014], "revenue": [{"year": 2018, "value": 75822.0}, {"year": 2017, "value": 66919.0}, {"year": 2016, "value": 55762.0}, {"year": 2015, "value": 68945.0}, {"year": 2014, "value": 110948.0}], "operatingProfit": [{"year": 2018, "value": 0}, {"year": 2017, "value": 7439.0}, {"year": 2016, "value": 1041.0}, {"year": 2015, "value": -5523.0}, {"year": 2014, "value": 8136.0}], "earnings": [{"year": 2018, "value": 4126.0}, {"year": 2017, "value": 3374.0}, {"year": 2016, "value": -1464.0}, {"year": 2015, "value": -8783.0}, {"year": 2014, "value": 1291.0}], "bookValuePerShare": [{"year": 2018, "value": 14.17}, {"year": 2017, "value": 13.34}, {"year": 2016, "value": 15.13}, {"year": 2015, "value": 14.37}, {"year": 2014, "value": 16.59}], "cashFlow": [{"year": 2018, "value": 13647.0}, {"year": 2017, "value": 10117.0}, {"year": 2016, "value": 7673.0}, {"year": 2015, "value": 11903.0}, {"year": 2014, "value": 15110.0}], "cashFlowFromInvestments": [{"year": 2018, "value": -7536.0}, {"year": 2017, "value": -3768.0}, {"year": 2016, "value": -4443.0}, {"year": 2015, "value": -11177.0}, {"year": 2014, "value": -8943.0}], "cashFlowFromFinance": [{"year": 2018, "value": -2637.0}, {"year": 2017, "value": -4595.0}, {"year": 2016, "value": -3651.0}, {"year": 2015, "value": -1351.0}, {"year": 2014, "value": -5062.0}], "cashReserveDelta": [{"year": 2018, "value": 3806.0}, {"year": 2017, "value": 1504.0}, {"year": 2016, "value": 1568.0}, {"year": 2015, "value": -1385.0}, {"year": 2014, "value": 1368.0}], "cashReserveEndOfPeriod": [{"year": 2018, "value": 17388.0}, {"year": 2017, "value": 13582.0}, {"year": 2016, "value": 12078.0}, {"year": 2015, "value": 10510.0}, {"year": 2014, "value": 11895.0}], "amountOfSharesOutstanding": [{"year": 2018, "value": 3601.14}, {"year": 2017, "value": 3601.14}, {"year": 2016, "value": 3601.14}, {"year": 2015, "value": 3601.14}, {"year": 2014, "value": 3610.39}], "earningsPerShare": [{"year": 2018, "value": 1.15}, {"year": 2017, "value": 0.94}, {"year": 2016, "value": -0.41}, {"year": 2015, "value": -2.44}, {"year": 2014, "value": 0.36}], "dividendPerShare": [{"year": 2018, "value": 0.83}, {"year": 2017, "value": 0.4}, {"year": 2016, "value": 0.8}, {"year": 2015, "value": 0.8}, {"year": 2014, "value": 1.12}], "dividend": [{"year": 2018, "value": 2988.95}, {"year": 2017, "value": 1440.46}, {"year": 2016, "value": 2882.0}, {"year": 2015, "value": 2880.0}, {"year": 2014, "value": 4037.0}], "revenuePerStock": [{"year": 2018, "value": 20.86}, {"year": 2017, "value": 18.41}, {"year": 2016, "value": 15.34}, {"year": 2015, "value": 18.97}, {"year": 2014, "value": 30.53}], "cashFlowPerStock": [{"year": 2018, "value": 3.76}, {"year": 2017, "value": 2.78}, {"year": 2016, "value": 2.11}, {"year": 2015, "value": 3.28}, {"year": 2014, "value": 4.16}], "returnOnEquity": [{"year": 2018, "value": 8.09}, {"year": 2017, "value": 7.02}, {"year": 2016, "value": -2.69}, {"year": 2015, "value": -16.97}, {"year": 2014, "value": 2.16}], "returnOnRevenue": [{"year": 2018, "value": 5.44}, {"year": 2017, "value": 5.04}, {"year": 2016, "value": -2.63}, {"year": 2015, "value": -12.74}, {"year": 2014, "value": 1.16}], "totalReturn": [{"year": 2018, "value": 4.06}, {"year": 2017, "value": 3.59}, {"year": 2016, "value": -0.57}, {"year": 2015, "value": -5.89}, {"year": 2014, "value": 1.51}], "returnOnInvest": [{"year": 2018, "value": 3.49}, {"year": 2017, "value": 2.94}, {"year": 2016, "value": -1.18}, {"year": 2015, "value": -6.52}, {"year": 2014, "value": 0.88}], "shareOfLongTermAssets": [{"year": 2018, "value": 66.67}, {"year": 2017, "value": 68.02}, {"year": 2016, "value": 69.5}, {"year": 2015, "value": 57.34}, {"year": 2014, "value": 62.48}], "shareOfCurrentAssets": [{"year": 2018, "value": 33.33}, {"year": 2017, "value": 31.7}, {"year": 2016, "value": 30.5}, {"year": 2015, "value": 42.66}, {"year": 2014, "value": 37.52}], "shareOfEquity": [{"year": 2018, "value": 43.1}, {"year": 2017, "value": 41.79}, {"year": 2016, "value": 43.74}, {"year": 2015, "value": 38.39}, {"year": 2014, "value": 40.87}], "debtToEquityRatio": [{"year": 2018, "value": 132.03}, {"year": 2017, "value": 139.28}, {"year": 2016, "value": 128.62}, {"year": 2015, "value": 160.45}, {"year": 2014, "value": 144.68}], "firstGradeLiquidity": [{"year": 2018, "value": 61.26}, {"year": 2017, "value": 54.91}, {"year": 2016, "value": 43.61}, {"year": 2015, "value": 28.69}, {"year": 2014, "value": 31.86}], "secondGradeLiquidity": [{"year": 2018, "value": 94.81}, {"year": 2017, "value": 96.07}, {"year": 2016, "value": 84.0}, {"year": 2015, "value": 61.5}, {"year": 2014, "value": 84.64}], "thirdGradeLiquidity": [{"year": 2018, "value": 111.19}, {"year": 2017, "value": 114.76}, {"year": 2016, "value": 100.74}, {"year": 2015, "value": 72.18}, {"year": 2014, "value": 104.87}], "firstCoverageRatio": [{"year": 2018, "value": 64.64}, {"year": 2017, "value": 61.44}, {"year": 2016, "value": 62.94}, {"year": 2015, "value": 66.96}, {"year": 2014, "value": 65.42}], "secondCoverageRatio": [{"year": 2018, "value": 113.88}, {"year": 2017, "value": 115.2}, {"year": 2016, "value": 113.49}, {"year": 2015, "value": 124.51}, {"year": 2014, "value": 116.5}], "thirdCoverageRatio": [{"year": 2018, "value": 107.54}, {"year": 2017, "value": 108.77}, {"year": 2016, "value": 107.72}, {"year": 2015, "value": 118.52}, {"year": 2014, "value": 107.6}], "gearingRatio": [{"year": 2018, "value": 56.9}, {"year": 2017, "value": 58.21}, {"year": 2016, "value": 56.26}, {"year": 2015, "value": 61.61}, {"year": 2014, "value": 59.13}], "amountOfEmployees": [{"year": 2018, "value": 31701.0}, {"year": 2017, "value": 32934.0}, {"year": 2016, "value": 33536.0}, {"year": 2015, "value": 29053.0}, {"year": 2014, "value": 84405.0}], "laborCost": [{"year": 2018, "value": 3093.0}, {"year": 2017, "value": 2951.0}, {"year": 2016, "value": 2994.0}, {"year": 2015, "value": 2778.0}, {"year": 2014, "value": 5337.0}], "revenuePerEmployee": [{"year": 2018, "value": 2391785.75}, {"year": 2017, "value": 2031912.31}, {"year": 2016, "value": 1662750.48}, {"year": 2015, "value": 2373076.79}, {"year": 2014, "value": 1314471.89}]}}