{"balance_sheet": {"years": [2018, 2017, 2016, 2015, 2014], "assets": {"Kassenbestand und Guthaben bei Kreditinstituten": [{"year": 2018, "value": 4915.0}, {"year": 2017, "value": 5863.0}, {"year": 2016, "value": 7149.0}, {"year": 2015, "value": 6131.0}, {"year": 2014, "value": 10098.0}], "Forderungen aus Lieferungen und Leistungen": [{"year": 2018, "value": 712.0}, {"year": 2017, "value": 695.0}, {"year": 2016, "value": 592.0}, {"year": 2015, "value": 619.0}, {"year": 2014, "value": 11342.0}], "Vorr\u00e4te": [{"year": 2018, "value": 0.0}, {"year": 2017, "value": 0.0}, {"year": 2016, "value": 0.0}, {"year": 2015, "value": 0.0}, {"year": 2014, "value": 0.0}], "Sonstiges Umlaufverm\u00f6gen": [{"year": 2018, "value": 1499.0}, {"year": 2017, "value": 1185.0}, {"year": 2016, "value": 1134.0}, {"year": 2015, "value": 1154.0}, {"year": 2014, "value": 5091.0}], "Summe Umlaufverm\u00f6gen": [{"year": 2018, "value": 7126.0}, {"year": 2017, "value": 7743.0}, {"year": 2016, "value": 8875.0}, {"year": 2015, "value": 7904.0}, {"year": 2014, "value": 26531.0}], "Sachanlagen": [{"year": 2018, "value": 1597.0}, {"year": 2017, "value": 1597.0}, {"year": 2016, "value": 1516.0}, {"year": 2015, "value": 1554.0}, {"year": 2014, "value": 2902.0}], "Immaterielle Verm\u00f6gensgegenst\u00e4nde": [{"year": 2018, "value": 5252.0}, {"year": 2017, "value": 4842.0}, {"year": 2016, "value": 4603.0}, {"year": 2015, "value": 4541.0}, {"year": 2014, "value": 9658.0}], "Goodwill": [{"year": 2018, "value": 5160.0}, {"year": 2017, "value": 4773.0}, {"year": 2016, "value": 4501.0}, {"year": 2015, "value": 4451.0}, {"year": 2014, "value": 9094.0}], "Finanzanlagen": [{"year": 2018, "value": 3778.0}, {"year": 2017, "value": 6331.0}, {"year": 2016, "value": 3969.0}, {"year": 2015, "value": 3391.0}, {"year": 2014, "value": 5777.0}], "Summe Anlageverm\u00f6gen": [{"year": 2018, "value": 15693.0}, {"year": 2017, "value": 18238.0}, {"year": 2016, "value": 14972.0}, {"year": 2015, "value": 9881.0}, {"year": 2014, "value": 18601.0}], "Latente Steuern": [{"year": 2018, "value": 4792.0}, {"year": 2017, "value": 5195.0}, {"year": 2016, "value": 4608.0}, {"year": 2015, "value": 0.0}, {"year": 2014, "value": 0}], "Summe Aktiva": [{"year": 2018, "value": 22819.0}, {"year": 2017, "value": 25981.0}, {"year": 2016, "value": 23847.0}, {"year": 2015, "value": 17785.0}, {"year": 2014, "value": 45132.0}]}, "liabilities_and_equity": {"Kurzfristige Finanzverbindlichkeiten": [{"year": 2018, "value": 1546.0}, {"year": 2017, "value": 781.0}, {"year": 2016, "value": 1451.0}, {"year": 2015, "value": 0.0}, {"year": 2014, "value": 850.0}], "Verbindlichkeiten aus Lieferung und Leistung": [{"year": 2018, "value": 286.0}, {"year": 2017, "value": 330.0}, {"year": 2016, "value": 283.0}, {"year": 2015, "value": 349.0}, {"year": 2014, "value": 10946.0}], "Sonstiges kurzfristiges Fremdkapital": [{"year": 2018, "value": 2505.0}, {"year": 2017, "value": 2251.0}, {"year": 2016, "value": 2003.0}, {"year": 2015, "value": 1842.0}, {"year": 2014, "value": 5581.0}], "Verbindlichkeiten aus laufender Steuer": [{"year": 2018, "value": 117.0}, {"year": 2017, "value": 177.0}, {"year": 2016, "value": 110.0}, {"year": 2015, "value": 72.0}, {"year": 2014, "value": 154.0}], "Summe kurzfristiges Fremdkapital": [{"year": 2018, "value": 4454.0}, {"year": 2017, "value": 3539.0}, {"year": 2016, "value": 3847.0}, {"year": 2015, "value": 2263.0}, {"year": 2014, "value": 17531.0}], "Langfristige Finanzverbindlichkeiten": [{"year": 2018, "value": 7685.0}, {"year": 2017, "value": 9234.0}, {"year": 2016, "value": 7509.0}, {"year": 2015, "value": 6779.0}, {"year": 2014, "value": 6777.0}], "Summe langfristiges Fremdkapital": [{"year": 2018, "value": 12084.0}, {"year": 2017, "value": 14379.0}, {"year": 2016, "value": 9461.0}, {"year": 2015, "value": 8946.0}, {"year": 2014, "value": 7695.0}], "Minderheitenanteil": [{"year": 2018, "value": 0.0}, {"year": 2017, "value": 0.0}, {"year": 2016, "value": 0.0}, {"year": 2015, "value": 0.0}, {"year": 2014, "value": 0.0}], "Rechnungsabgrenzungsposten": [{"year": 2018, "value": 170.0}, {"year": 2017, "value": 117.0}, {"year": 2016, "value": 110.0}, {"year": 2015, "value": 106.0}, {"year": 2014, "value": 188.0}], "Latente Steuern": [{"year": 2018, "value": 2925.0}, {"year": 2017, "value": 3425.0}, {"year": 2016, "value": 1888.0}, {"year": 2015, "value": 2092.0}, {"year": 2014, "value": 792.0}], "Summe Fremdkapital": [{"year": 2018, "value": 16538.0}, {"year": 2017, "value": 17918.0}, {"year": 2016, "value": 13308.0}, {"year": 2015, "value": 11209.0}, {"year": 2014, "value": 25226.0}], "Eigene Aktien": [{"year": 2018, "value": -26394.0}, {"year": 2017, "value": -21892.0}, {"year": 2016, "value": -19205.0}, {"year": 2015, "value": -16203.0}, {"year": 2014, "value": -14054.0}], "Sonstiges Kapital": [{"year": 2018, "value": 499.08}, {"year": 2017, "value": 717.99}, {"year": 2016, "value": -123.64}, {"year": 2015, "value": 526.37}, {"year": 2014, "value": 1171.39}], "Gezeichnetes Kapital (Grundkapital)": [{"year": 2018, "value": 0.92}, {"year": 2017, "value": 1.01}, {"year": 2016, "value": 1.64}, {"year": 2015, "value": 1.63}, {"year": 2014, "value": 1.61}], "Kapitalr\u00fccklagen": [{"year": 2018, "value": 15716.0}, {"year": 2017, "value": 15293.0}, {"year": 2016, "value": 14907.0}, {"year": 2015, "value": 14538.0}, {"year": 2014, "value": 13887.0}], "Gewinnr\u00fccklagen": [{"year": 2018, "value": 16459.0}, {"year": 2017, "value": 13943.0}, {"year": 2016, "value": 14959.0}, {"year": 2015, "value": 7713.0}, {"year": 2014, "value": 18900.0}], "wirtschaftliches Eigenkapital": [{"year": 2018, "value": 6281.0}, {"year": 2017, "value": 8063.0}, {"year": 2016, "value": 10539.0}, {"year": 2015, "value": 6576.0}, {"year": 2014, "value": 19906.0}], "Summe Eigenkapital": [{"year": 2018, "value": 6281.0}, {"year": 2017, "value": 8063.0}, {"year": 2016, "value": 10539.0}, {"year": 2015, "value": 6576.0}, {"year": 2014, "value": 19906.0}], "Summe Passiva": [{"year": 2018, "value": 22819.0}, {"year": 2017, "value": 25981.0}, {"year": 2016, "value": 23847.0}, {"year": 2015, "value": 17785.0}, {"year": 2014, "value": 45132.0}]}}, "head": {"title": "eBay", "current_price": {"value": 38.55, "currency": "USD"}, "isin": "US2786421030", "wkn": "916529", "timestamp": "2019-10-12 18:28:31", "url": "https://kurse.boerse.ard.de/ard/kurse_einzelkurs_profil.htn?i=38852"}, "owner_structure": [{"owner": "Streubesitz", "percent": 0.811}, {"owner": "The Vanguard Group", "percent": 0.068}, {"owner": "BlackRock, Inc.", "percent": 0.062}, {"owner": "Pierre M. Omidyar", "percent": 0.059}], "kpi": {"years": [2018, 2017, 2016, 2015, 2014], "revenue": [{"year": 2018, "value": 10746.0}, {"year": 2017, "value": 9567.0}, {"year": 2016, "value": 8979.0}, {"year": 2015, "value": 8592.0}, {"year": 2014, "value": 17902.0}], "researchAndDevelopment": [{"year": 2018, "value": 1285.0}, {"year": 2017, "value": 1224.0}, {"year": 2016, "value": 1114.0}, {"year": 2015, "value": 923.0}, {"year": 2014, "value": 2000.0}], "operatingProfit": [{"year": 2018, "value": 2870.0}, {"year": 2017, "value": 2387.0}, {"year": 2016, "value": 3732.0}, {"year": 2015, "value": 2231.0}, {"year": 2014, "value": 3521.0}], "earnings": [{"year": 2018, "value": 2530.0}, {"year": 2017, "value": -1016.0}, {"year": 2016, "value": 7266.0}, {"year": 2015, "value": 1725.0}, {"year": 2014, "value": 46.0}], "bookValuePerShare": [{"year": 2018, "value": 41.32}, {"year": 2017, "value": 21.21}, {"year": 2016, "value": 9.7}, {"year": 2015, "value": 5.55}, {"year": 2014, "value": 16.26}], "cashFlow": [{"year": 2018, "value": 2658.0}, {"year": 2017, "value": 3146.0}, {"year": 2016, "value": 2826.0}, {"year": 2015, "value": 4033.0}, {"year": 2014, "value": 5677.0}], "cashFlowFromInvestments": [{"year": 2018, "value": 2894.0}, {"year": 2017, "value": -1296.0}, {"year": 2016, "value": -2008.0}, {"year": 2015, "value": -3611.0}, {"year": 2014, "value": -2673.0}], "cashFlowFromFinance": [{"year": 2018, "value": -5398.0}, {"year": 2017, "value": -1784.0}, {"year": 2016, "value": -744.0}, {"year": 2015, "value": -4554.0}, {"year": 2014, "value": -1022.0}], "cashReserveDelta": [{"year": 2018, "value": -948.0}, {"year": 2017, "value": -1286.0}, {"year": 2016, "value": 1018.0}, {"year": 2015, "value": -3967.0}, {"year": 2014, "value": 1073.0}], "cashReserveEndOfPeriod": [{"year": 2018, "value": 4915.0}, {"year": 2017, "value": 5863.0}, {"year": 2016, "value": 7149.0}, {"year": 2015, "value": 6131.0}, {"year": 2014, "value": 10098.0}], "amountOfSharesOutstanding": [{"year": 2018, "value": 991.0}, {"year": 2017, "value": 1064.0}, {"year": 2016, "value": 1144.0}, {"year": 2015, "value": 1220.0}, {"year": 2014, "value": 1251.0}], "earningsPerShare": [{"year": 2018, "value": 2.55}, {"year": 2017, "value": -0.95}, {"year": 2016, "value": 6.35}, {"year": 2015, "value": 1.42}, {"year": 2014, "value": 0.04}], "dividendPerShare": [{"year": 2018, "value": 0.0}, {"year": 2017, "value": 0.0}, {"year": 2016, "value": 0.0}, {"year": 2015, "value": 0.0}, {"year": 2014, "value": 0.0}], "dividend": [{"year": 2018, "value": 0.0}, {"year": 2017, "value": 0.0}, {"year": 2016, "value": 0.0}, {"year": 2015, "value": 0.0}, {"year": 2014, "value": 0.0}], "revenuePerStock": [{"year": 2018, "value": 11.74}, {"year": 2017, "value": 9.45}, {"year": 2016, "value": 5.46}, {"year": 2015, "value": 5.28}, {"year": 2014, "value": 11.13}], "cashFlowPerStock": [{"year": 2018, "value": 2.9}, {"year": 2017, "value": 3.11}, {"year": 2016, "value": 1.72}, {"year": 2015, "value": 2.48}, {"year": 2014, "value": 3.53}], "returnOnEquity": [{"year": 2018, "value": 40.28}, {"year": 2017, "value": -12.6}, {"year": 2016, "value": 68.94}, {"year": 2015, "value": 26.23}, {"year": 2014, "value": 0.23}], "returnOnRevenue": [{"year": 2018, "value": 23.54}, {"year": 2017, "value": -10.62}, {"year": 2016, "value": 80.92}, {"year": 2015, "value": 20.08}, {"year": 2014, "value": 0.26}], "totalReturn": [{"year": 2018, "value": 12.52}, {"year": 2017, "value": -2.79}, {"year": 2016, "value": 31.41}, {"year": 2015, "value": 10.51}, {"year": 2014, "value": 0.37}], "returnOnInvest": [{"year": 2018, "value": 11.09}, {"year": 2017, "value": -3.91}, {"year": 2016, "value": 30.47}, {"year": 2015, "value": 9.7}, {"year": 2014, "value": 0.1}], "shareOfLongTermAssets": [{"year": 2018, "value": 68.77}, {"year": 2017, "value": 70.2}, {"year": 2016, "value": 62.78}, {"year": 2015, "value": 55.56}, {"year": 2014, "value": 41.21}], "shareOfCurrentAssets": [{"year": 2018, "value": 31.23}, {"year": 2017, "value": 29.8}, {"year": 2016, "value": 37.22}, {"year": 2015, "value": 44.44}, {"year": 2014, "value": 58.79}], "shareOfEquity": [{"year": 2018, "value": 27.53}, {"year": 2017, "value": 31.03}, {"year": 2016, "value": 44.19}, {"year": 2015, "value": 36.97}, {"year": 2014, "value": 44.11}], "debtToEquityRatio": [{"year": 2018, "value": 263.3}, {"year": 2017, "value": 222.22}, {"year": 2016, "value": 126.27}, {"year": 2015, "value": 170.45}, {"year": 2014, "value": 126.73}], "firstGradeLiquidity": [{"year": 2018, "value": 110.35}, {"year": 2017, "value": 165.67}, {"year": 2016, "value": 185.83}, {"year": 2015, "value": 270.92}, {"year": 2014, "value": 57.6}], "secondGradeLiquidity": [{"year": 2018, "value": 126.34}, {"year": 2017, "value": 185.31}, {"year": 2016, "value": 201.22}, {"year": 2015, "value": 298.28}, {"year": 2014, "value": 122.3}], "thirdGradeLiquidity": [{"year": 2018, "value": 126.34}, {"year": 2017, "value": 185.31}, {"year": 2016, "value": 201.22}, {"year": 2015, "value": 298.28}, {"year": 2014, "value": 122.3}], "firstCoverageRatio": [{"year": 2018, "value": 40.02}, {"year": 2017, "value": 44.21}, {"year": 2016, "value": 70.39}, {"year": 2015, "value": 66.55}, {"year": 2014, "value": 107.02}], "secondCoverageRatio": [{"year": 2018, "value": 117.03}, {"year": 2017, "value": 123.05}, {"year": 2016, "value": 133.58}, {"year": 2015, "value": 157.09}, {"year": 2014, "value": 148.38}], "thirdCoverageRatio": [{"year": 2018, "value": 117.03}, {"year": 2017, "value": 123.05}, {"year": 2016, "value": 133.58}, {"year": 2015, "value": 157.09}, {"year": 2014, "value": 148.38}], "gearingRatio": [{"year": 2018, "value": 72.47}, {"year": 2017, "value": 68.97}, {"year": 2016, "value": 55.81}, {"year": 2015, "value": 63.03}, {"year": 2014, "value": 55.89}], "amountOfEmployees": [{"year": 2018, "value": 14000.0}, {"year": 2017, "value": 14100.0}, {"year": 2016, "value": 12600.0}, {"year": 2015, "value": 11600.0}, {"year": 2014, "value": 36500.0}], "revenuePerEmployee": [{"year": 2018, "value": 767571.43}, {"year": 2017, "value": 678510.64}, {"year": 2016, "value": 712619.05}, {"year": 2015, "value": 740689.66}, {"year": 2014, "value": 490465.75}]}}