{"balance_sheet": {"years": [2018, 2017, 2016, 2015, 2014], "assets": {"Kassenbestand und Guthaben bei Kreditinstituten": [{"year": 2018, "value": 96.6}, {"year": 2017, "value": 186.8}, {"year": 2016, "value": 118.4}, {"year": 2015, "value": 112.6}, {"year": 2014, "value": 77.3}], "Forderungen aus Lieferungen und Leistungen": [{"year": 2018, "value": 518.1}, {"year": 2017, "value": 555.1}, {"year": 2016, "value": 465.2}, {"year": 2015, "value": 455.2}, {"year": 2014, "value": 493.6}], "Vorr\u00e4te": [{"year": 2018, "value": 786.3}, {"year": 2017, "value": 793.3}, {"year": 2016, "value": 756.3}, {"year": 2015, "value": 710.8}, {"year": 2014, "value": 713.8}], "Sonstiges Umlaufverm\u00f6gen": [{"year": 2018, "value": 78.9}, {"year": 2017, "value": 81.8}, {"year": 2016, "value": 81.9}, {"year": 2015, "value": 127.9}, {"year": 2014, "value": 131.5}], "Summe Umlaufverm\u00f6gen": [{"year": 2018, "value": 1479.9}, {"year": 2017, "value": 1617.0}, {"year": 2016, "value": 1421.8}, {"year": 2015, "value": 1406.5}, {"year": 2014, "value": 1416.2}], "Sachanlagen": [{"year": 2018, "value": 985.1}, {"year": 2017, "value": 809.1}, {"year": 2016, "value": 669.4}, {"year": 2015, "value": 618.4}, {"year": 2014, "value": 602.7}], "Immaterielle Verm\u00f6gensgegenst\u00e4nde": [{"year": 2018, "value": 7401.2}, {"year": 2017, "value": 7561.2}, {"year": 2016, "value": 2196.3}, {"year": 2015, "value": 2131.4}, {"year": 2014, "value": 2053.0}], "Goodwill": [{"year": 2018, "value": 4527.9}, {"year": 2017, "value": 4490.1}, {"year": 2016, "value": 1771.4}, {"year": 2015, "value": 1759.3}, {"year": 2014, "value": 1722.2}], "Finanzanlagen": [{"year": 2018, "value": 390.2}, {"year": 2017, "value": 398.5}, {"year": 2016, "value": 348.4}, {"year": 2015, "value": 351.5}, {"year": 2014, "value": 352.4}], "Summe Anlageverm\u00f6gen": [{"year": 2018, "value": 8776.5}, {"year": 2017, "value": 8768.8}, {"year": 2016, "value": 3214.1}, {"year": 2015, "value": 3101.3}, {"year": 2014, "value": 2998.1}], "Summe Aktiva": [{"year": 2018, "value": 10256.4}, {"year": 2017, "value": 10385.8}, {"year": 2016, "value": 4635.9}, {"year": 2015, "value": 4507.8}, {"year": 2014, "value": 4414.3}]}, "liabilities_and_equity": {"Kurzfristige Finanzverbindlichkeiten": [{"year": 2018, "value": 643.5}, {"year": 2017, "value": 583.2}, {"year": 2016, "value": 393.2}, {"year": 2015, "value": 343.0}, {"year": 2014, "value": 270.8}], "Verbindlichkeiten aus Lieferung und Leistung": [{"year": 2018, "value": 710.0}, {"year": 2017, "value": 639.9}, {"year": 2016, "value": 450.8}, {"year": 2015, "value": 411.9}, {"year": 2014, "value": 372.1}], "Sonstiges kurzfristiges Fremdkapital": [{"year": 2018, "value": 648.2}, {"year": 2017, "value": 724.2}, {"year": 2016, "value": 578.7}, {"year": 2015, "value": 485.3}, {"year": 2014, "value": 479.1}], "Summe kurzfristiges Fremdkapital": [{"year": 2018, "value": 2001.7}, {"year": 2017, "value": 1947.3}, {"year": 2016, "value": 1422.7}, {"year": 2015, "value": 1240.2}, {"year": 2014, "value": 1122.0}], "Langfristige Finanzverbindlichkeiten": [{"year": 2018, "value": 4052.9}, {"year": 2017, "value": 4443.9}, {"year": 2016, "value": 1054.0}, {"year": 2015, "value": 1052.7}, {"year": 2014, "value": 1014.1}], "Summe langfristiges Fremdkapital": [{"year": 2018, "value": 5072.5}, {"year": 2017, "value": 5867.6}, {"year": 2016, "value": 1575.1}, {"year": 2015, "value": 1580.7}, {"year": 2014, "value": 1482.9}], "Minderheitenanteil": [{"year": 2018, "value": 11.3}, {"year": 2017, "value": 11.0}, {"year": 2016, "value": 11.5}, {"year": 2015, "value": 16.7}, {"year": 2014, "value": 17.2}], "Summe Fremdkapital": [{"year": 2018, "value": 7074.2}, {"year": 2017, "value": 7814.9}, {"year": 2016, "value": 2997.8}, {"year": 2015, "value": 2820.9}, {"year": 2014, "value": 2604.9}], "Sonstiges Kapital": [{"year": 2018, "value": -348.6}, {"year": 2017, "value": -268.5}, {"year": 2016, "value": -514.4}, {"year": 2015, "value": -406.1}, {"year": 2014, "value": -186.0}], "Gezeichnetes Kapital (Grundkapital)": [{"year": 2018, "value": 1770.6}, {"year": 2017, "value": 1672.9}, {"year": 2016, "value": 1084.2}, {"year": 2015, "value": 1039.6}, {"year": 2014, "value": 995.6}], "Gewinnr\u00fccklagen": [{"year": 2018, "value": 1760.2}, {"year": 2017, "value": 1166.5}, {"year": 2016, "value": 1056.8}, {"year": 2015, "value": 1036.7}, {"year": 2014, "value": 982.6}], "wirtschaftliches Eigenkapital": [{"year": 2018, "value": 2902.1}, {"year": 2017, "value": 2326.18}, {"year": 2016, "value": 0}, {"year": 2015, "value": 0}, {"year": 2014, "value": 0}], "Summe Eigenkapital": [{"year": 2018, "value": 3182.2}, {"year": 2017, "value": 2570.9}, {"year": 2016, "value": 1626.6}, {"year": 2015, "value": 1670.2}, {"year": 2014, "value": 1792.2}], "Summe Passiva": [{"year": 2018, "value": 10256.4}, {"year": 2017, "value": 10385.8}, {"year": 2016, "value": 4635.9}, {"year": 2015, "value": 4507.8}, {"year": 2014, "value": 4414.3}]}}, "head": {"title": "McCormick & Company", "current_price": {"value": 164.76, "currency": "USD"}, "isin": "US5797802064", "wkn": "858250", "timestamp": "2019-10-12 18:23:48", "url": "https://kurse.boerse.ard.de/ard/kurse_einzelkurs_profil.htn?i=57568"}, "owner_structure": [{"owner": "Streubesitz", "percent": 0.708}, {"owner": "McCormick 401 (k)...", "percent": 0.185}, {"owner": "Alan D. Wilson", "percent": 0.107}], "kpi": {"years": [2018, 2017, 2016, 2015, 2014], "revenue": [{"year": 2018, "value": 5408.9}, {"year": 2017, "value": 4834.1}, {"year": 2016, "value": 4411.5}, {"year": 2015, "value": 4296.3}, {"year": 2014, "value": 4243.2}], "researchAndDevelopment": [{"year": 2018, "value": 69.4}, {"year": 2017, "value": 66.1}, {"year": 2016, "value": 61.0}, {"year": 2015, "value": 60.8}, {"year": 2014, "value": 62.0}], "operatingProfit": [{"year": 2018, "value": 950.7}, {"year": 2017, "value": 724.4}, {"year": 2016, "value": 645.2}, {"year": 2015, "value": 549.5}, {"year": 2014, "value": 604.1}], "earnings": [{"year": 2018, "value": 933.4}, {"year": 2017, "value": 477.4}, {"year": 2016, "value": 472.3}, {"year": 2015, "value": 401.6}, {"year": 2014, "value": 437.9}], "bookValuePerShare": [{"year": 2018, "value": 24.09}, {"year": 2017, "value": 19.63}, {"year": 2016, "value": 12.98}, {"year": 2015, "value": 13.12}, {"year": 2014, "value": 13.96}], "cashFlow": [{"year": 2018, "value": 821.2}, {"year": 2017, "value": 815.3}, {"year": 2016, "value": 658.1}, {"year": 2015, "value": 590.0}, {"year": 2014, "value": 503.6}], "cashFlowFromInvestments": [{"year": 2018, "value": -158.5}, {"year": 2017, "value": -4508.3}, {"year": 2016, "value": -267.1}, {"year": 2015, "value": -338.9}, {"year": 2014, "value": -131.6}], "cashFlowFromFinance": [{"year": 2018, "value": -751.1}, {"year": 2017, "value": 3756.0}, {"year": 2016, "value": -371.5}, {"year": 2015, "value": -199.6}, {"year": 2014, "value": -348.9}], "cashReserveDelta": [{"year": 2018, "value": -90.2}, {"year": 2017, "value": 68.4}, {"year": 2016, "value": 5.8}, {"year": 2015, "value": 35.3}, {"year": 2014, "value": 14.3}], "cashReserveEndOfPeriod": [{"year": 2018, "value": 96.6}, {"year": 2017, "value": 186.8}, {"year": 2016, "value": 118.4}, {"year": 2015, "value": 112.6}, {"year": 2014, "value": 77.3}], "amountOfSharesOutstanding": [{"year": 2018, "value": 133.2}, {"year": 2017, "value": 128.4}, {"year": 2016, "value": 128.0}, {"year": 2015, "value": 129.2}, {"year": 2014, "value": 0}], "earningsPerShare": [{"year": 2018, "value": 7.0}, {"year": 2017, "value": 3.72}, {"year": 2016, "value": 3.69}, {"year": 2015, "value": 3.11}, {"year": 2014, "value": 3.34}], "dividendPerShare": [{"year": 2018, "value": 2.08}, {"year": 2017, "value": 1.88}, {"year": 2016, "value": 1.72}, {"year": 2015, "value": 1.6}, {"year": 2014, "value": 1.48}], "dividend": [{"year": 2018, "value": 280.1}, {"year": 2017, "value": 244.72}, {"year": 2016, "value": 0}, {"year": 2015, "value": 0}, {"year": 2014, "value": 0}], "revenuePerStock": [{"year": 2018, "value": 40.95}, {"year": 2017, "value": 36.9}, {"year": 2016, "value": 35.21}, {"year": 2015, "value": 33.75}, {"year": 2014, "value": 33.05}], "cashFlowPerStock": [{"year": 2018, "value": 6.22}, {"year": 2017, "value": 6.22}, {"year": 2016, "value": 5.25}, {"year": 2015, "value": 4.63}, {"year": 2014, "value": 3.92}], "returnOnEquity": [{"year": 2018, "value": 29.33}, {"year": 2017, "value": 18.57}, {"year": 2016, "value": 29.04}, {"year": 2015, "value": 24.05}, {"year": 2014, "value": 24.43}], "returnOnRevenue": [{"year": 2018, "value": 17.26}, {"year": 2017, "value": 9.88}, {"year": 2016, "value": 10.71}, {"year": 2015, "value": 9.35}, {"year": 2014, "value": 10.32}], "totalReturn": [{"year": 2018, "value": 10.8}, {"year": 2017, "value": 5.52}, {"year": 2016, "value": 11.4}, {"year": 2015, "value": 10.09}, {"year": 2014, "value": 11.05}], "returnOnInvest": [{"year": 2018, "value": 9.1}, {"year": 2017, "value": 4.6}, {"year": 2016, "value": 10.19}, {"year": 2015, "value": 8.91}, {"year": 2014, "value": 9.92}], "shareOfLongTermAssets": [{"year": 2018, "value": 85.57}, {"year": 2017, "value": 84.43}, {"year": 2016, "value": 69.33}, {"year": 2015, "value": 68.8}, {"year": 2014, "value": 67.92}], "shareOfCurrentAssets": [{"year": 2018, "value": 14.43}, {"year": 2017, "value": 15.57}, {"year": 2016, "value": 30.67}, {"year": 2015, "value": 31.2}, {"year": 2014, "value": 32.08}], "shareOfEquity": [{"year": 2018, "value": 31.03}, {"year": 2017, "value": 24.75}, {"year": 2016, "value": 35.09}, {"year": 2015, "value": 37.05}, {"year": 2014, "value": 40.6}], "debtToEquityRatio": [{"year": 2018, "value": 222.31}, {"year": 2017, "value": 303.98}, {"year": 2016, "value": 185.01}, {"year": 2015, "value": 169.9}, {"year": 2014, "value": 146.31}], "firstGradeLiquidity": [{"year": 2018, "value": 4.83}, {"year": 2017, "value": 9.59}, {"year": 2016, "value": 8.32}, {"year": 2015, "value": 9.08}, {"year": 2014, "value": 6.89}], "secondGradeLiquidity": [{"year": 2018, "value": 30.71}, {"year": 2017, "value": 38.1}, {"year": 2016, "value": 41.02}, {"year": 2015, "value": 45.78}, {"year": 2014, "value": 50.88}], "thirdGradeLiquidity": [{"year": 2018, "value": 69.99}, {"year": 2017, "value": 78.84}, {"year": 2016, "value": 94.18}, {"year": 2015, "value": 103.1}, {"year": 2014, "value": 114.5}], "firstCoverageRatio": [{"year": 2018, "value": 36.26}, {"year": 2017, "value": 29.32}, {"year": 2016, "value": 50.61}, {"year": 2015, "value": 53.85}, {"year": 2014, "value": 59.78}], "secondCoverageRatio": [{"year": 2018, "value": 94.05}, {"year": 2017, "value": 96.23}, {"year": 2016, "value": 99.61}, {"year": 2015, "value": 104.82}, {"year": 2014, "value": 109.24}], "thirdCoverageRatio": [{"year": 2018, "value": 86.32}, {"year": 2017, "value": 88.25}, {"year": 2016, "value": 80.64}, {"year": 2015, "value": 85.28}, {"year": 2014, "value": 88.23}], "gearingRatio": [{"year": 2018, "value": 68.97}, {"year": 2017, "value": 75.25}, {"year": 2016, "value": 64.91}, {"year": 2015, "value": 62.95}, {"year": 2014, "value": 59.4}], "amountOfEmployees": [{"year": 2018, "value": 11600.0}, {"year": 2017, "value": 11700.0}, {"year": 2016, "value": 10500.0}, {"year": 2015, "value": 10000.0}, {"year": 2014, "value": 10000.0}], "revenuePerEmployee": [{"year": 2018, "value": 466284.48}, {"year": 2017, "value": 413170.94}, {"year": 2016, "value": 420142.86}, {"year": 2015, "value": 429630.0}, {"year": 2014, "value": 424320.0}]}}